LICENSE
setup.py
boto_addins/__init__.py
boto_addins/lambda_.py
boto_addins/s3.py
boto_addins.egg-info/PKG-INFO
boto_addins.egg-info/SOURCES.txt
boto_addins.egg-info/dependency_links.txt
boto_addins.egg-info/requires.txt
boto_addins.egg-info/top_level.txt