Metadata-Version: 2.1
Name: boto-addins
Version: 0.9.11
Summary: Async proxy libraries for AWS services.
Home-page: http://packages.python.org/an_example_pypi_project
Author: Uploadcare
Author-email: ak@uploadcare.com
License: UNKNOWN
Keywords: aws amazon S3 storage lambda request-response invoke
Platform: UNKNOWN
License-File: LICENSE
